{
  "random_effects_system": {
    "description": "Sistema de efectos aleatorios basado en tabla de 8000 filas con distribución pseudo-normal",
    "table_size": 8000,
    "random_variable": "Distribución normal pseudo-aleatoria",
    "effect_types": [
      {
        "effect": "Causar daño",
        "damage_multiplier": 1.0,
        "damage_percentage": "100% de daño al contrario"
      },
      {
        "effect": "Causar daño crítico",
        "damage_multiplier_range": { "min": 1.2, "max": 1.8 },
        "damage_percentage": "120% a 180% de daño al contrario"
      },
      {
        "effect": "Evadir el golpe",
        "damage_multiplier": 0.8,
        "damage_percentage": "80% de daño al contrario"
      },
      {
        "effect": "Resistir el golpe",
        "damage_multiplier": 0.6,
        "damage_percentage": "60% de daño al contrario"
      },
      {
        "effect": "Escapar al golpe",
        "damage_multiplier": 0.2,
        "damage_percentage": "20% de daño al contrario"
      },
      {
        "effect": "No causar daño",
        "damage_multiplier": 0,
        "damage_percentage": "0% de daño al contrario"
      }
    ],
    "base_probabilities_by_hero": [
      {
        "hero": "Guerrero Tanque",
        "cause_damage": 0.40,
        "critical_damage": 0.00,
        "evade": 0.05,
        "resist": 0.00,
        "escape": 0.05,
        "no_damage": 0.50
      },
      {
        "hero": "Guerrero Armas",
        "cause_damage": 0.60,
        "critical_damage": 0.05,
        "evade": 0.03,
        "resist": 0.00,
        "escape": 0.02,
        "no_damage": 0.30
      },
      {
        "hero": "Mago Fuego",
        "cause_damage": 0.70,
        "critical_damage": 0.05,
        "evade": 0.00,
        "resist": 0.05,
        "escape": 0.00,
        "no_damage": 0.20
      },
      {
        "hero": "Mago Hielo",
        "cause_damage": 0.70,
        "critical_damage": 0.06,
        "evade": 0.00,
        "resist": 0.04,
        "escape": 0.00,
        "no_damage": 0.20
      },
      {
        "hero": "Pícaro Veneno",
        "cause_damage": 0.55,
        "critical_damage": 0.10,
        "evade": 0.00,
        "resist": 0.00,
        "escape": 0.00,
        "no_damage": 0.35
      },
      {
        "hero": "Pícaro Machete",
        "cause_damage": 0.60,
        "critical_damage": 0.08,
        "evade": 0.00,
        "resist": 0.00,
        "escape": 0.02,
        "no_damage": 0.30
      },
      {
        "hero": "Chamán",
        "cause_damage": 0.00,
        "critical_damage": 0.00,
        "evade": 0.00,
        "resist": 0.00,
        "escape": 0.00,
        "no_damage": 0.00,
        "note": "Solo sana, no ataca"
      },
      {
        "hero": "Médico",
        "cause_damage": 0.00,
        "critical_damage": 0.00,
        "evade": 0.00,
        "resist": 0.00,
        "escape": 0.00,
        "no_damage": 0.00,
        "note": "Solo sana, no ataca"
      }
    ],
    "example_guerrero_armas_base": {
      "hero": "Guerrero Armas",
      "table_distribution": [
        {
          "effect": "Causar daño",
          "percentage": 0.60,
          "rows": 4800,
          "range": "1-4800"
        },
        {
          "effect": "Causar daño crítico",
          "percentage": 0.05,
          "rows": 400,
          "range": "4801-5200"
        },
        {
          "effect": "Evadir el golpe",
          "percentage": 0.03,
          "rows": 240,
          "range": "5201-5440"
        },
        {
          "effect": "Resistir el golpe",
          "percentage": 0.00,
          "rows": 0,
          "range": null
        },
        {
          "effect": "Escapar al golpe",
          "percentage": 0.02,
          "rows": 160,
          "range": "5441-5600"
        },
        {
          "effect": "No causar daño",
          "percentage": 0.30,
          "rows": 2400,
          "range": "5601-8000"
        }
      ]
    },
    "example_guerrero_armas_with_6_percent_critical": {
      "hero": "Guerrero Armas con +6% crítico equipado",
      "note": "El crítico aumenta a costa de restar a 'no causar daño'",
      "table_distribution": [
        {
          "effect": "Causar daño",
          "percentage": 0.60,
          "rows": 4800,
          "range": "1-4800"
        },
        {
          "effect": "Causar daño crítico",
          "percentage": 0.11,
          "rows": 880,
          "range": "4801-5680"
        },
        {
          "effect": "Evadir el golpe",
          "percentage": 0.03,
          "rows": 240,
          "range": "5681-5920"
        },
        {
          "effect": "Resistir el golpe",
          "percentage": 0.00,
          "rows": 0,
          "range": null
        },
        {
          "effect": "Escapar al golpe",
          "percentage": 0.02,
          "rows": 160,
          "range": "5921-6080"
        },
        {
          "effect": "No causar daño",
          "percentage": 0.24,
          "rows": 1920,
          "range": "6081-8000"
        }
      ]
    },
    "equipment_rule": "Todo efecto que aumente en valor restará a 'No causar daño'. Los porcentajes deben sumar siempre el 100% de las 8000 filas."
  }
}